pyresource/__init__.py
pyresource/boolean.py
pyresource/conf.py
pyresource/django/executor.py
pyresource/django/operators.py
pyresource/django/resolver.py
pyresource/exceptions.py
pyresource/executor.py
pyresource/expression.py
pyresource/features.py
pyresource/field.py
pyresource/query.py
pyresource/resolver.py
pyresource/resource.py
pyresource/response.py
pyresource/schemas.py
pyresource/server.py
pyresource/space.py
pyresource/store.py
pyresource/translator.py
pyresource/types.py
pyresource/utils/__init__.py
pyresource/utils/types.py
pyresource/version.py
pyresource-0.1.0.dist-info/LICENSE.md
pyresource-0.1.0.dist-info/WHEEL
pyresource-0.1.0.dist-info/METADATA
pyresource-0.1.0.dist-info/RECORD
