Metadata-Version: 2.1
Name: pyresource
Version: 0.1.0
Summary: Resource is an SDK for building declarative, feature-rich REST APIs
Home-page: https://github.com/aleontiev/pyresource
License: MIT
Author: Anthony Leontiev
Author-email: ant@devlit.co
Requires-Python: >=3.7,<4.0
Classifier: License :: OSI Approved :: MIT License
Classifier: Programming Language :: Python :: 3
Classifier: Programming Language :: Python :: 3.7
Classifier: Programming Language :: Python :: 3.8
Requires-Dist: ttable (>=0.6.3,<0.7.0)
